aflabs_test/README.rst
aflabs_test/afuser/__init__.py
aflabs_test/afuser/admin.py
aflabs_test/afuser/apps.py
aflabs_test/afuser/forms.py
aflabs_test/afuser/migrations/__init__.py
aflabs_test/afuser/models.py
aflabs_test/afuser/tests.py
aflabs_test/afuser/urls.py
aflabs_test/afuser/views.py
aflabs_test/setup.cfg
aflabs_test/setup.py
aflabs_test-0.1.3.dist-info/METADATA
aflabs_test-0.1.3.dist-info/WHEEL
aflabs_test-0.1.3.dist-info/RECORD
