Metadata-Version: 2.1
Name: aflabs-test
Version: 0.1.3
Summary: this is a test for aflabs django app
Author: Ziga Avbreht
Author-email: ziga.avbreht@gmail.com
Requires-Python: >=3.11,<4.0
Classifier: Programming Language :: Python :: 3
Classifier: Programming Language :: Python :: 3.11
Requires-Dist: Django (>=4.2.2,<5.0.0)
